MANIFEST.in
README.md
README.rst
setup.py
ac/__init__.py
ac/ac.py
ac/filters.py
ac.egg-info/PKG-INFO
ac.egg-info/SOURCES.txt
ac.egg-info/dependency_links.txt
ac.egg-info/top_level.txt
ac.egg-info/zip-safe
src/__init__.py
src/ac/__init__.py
src/ac/ac.py