Metadata-Version: 1.0
Name: ac
Version: 0.3-alpha
Summary: A python library for writing C/C++ configure files.
Home-page: http://www.github.com/tomthorogood/AC.py
Author: Tom A. Thorogood
Author-email: tom@tomthorogood.com
License: GPLv3
Platform: UNKNOWN
